setup.py
pptable/__init__.py
pptable.egg-info/PKG-INFO
pptable.egg-info/SOURCES.txt
pptable.egg-info/dependency_links.txt
pptable.egg-info/top_level.txt
pptable.egg-info/zip-safe