Metadata-Version: 1.0
Name: pptable
Version: 0.0.3
Summary: pretty prints list of dictionaries as an ascii table
Home-page: http://github.com/munhitsu/pptable
Author: Mateusz Lapsa-Malawski
Author-email: m@cr3.io
License: MIT
Platform: any
